{
  "toix.capitalize": "IX: CapitalizeX",
  "toix.camelCase": "IX: Camel Case",
  "toix.dashCase": "IX: Dash Case",
  "toix.cycleCase": "IX: Cycle Case",
  "toix.spaceByUpper": "IX: Add Space before Uppercase",
  "toix.urlEncode": "IX: Url Encode",
  "toix.urlDecode": "IX: Url Decode",
  "toix.reverseAssignment": "IX: Reverse Assignment",
  "toix.unixToWinSlash": "IX: Unix To Win Slash",
  "toix.winToUnixSlash": "IX: Win To Unix Slash",
  "toix.singleToDoubleSlash": "IX: Single To Double Slash",
  "toix.doubleToSingleSlash": "IX: Separador duplo para simples",
  "toix.dashToUnderscore": "IX: Dash To Underscore",
  "toix.underscoreToDash": "IX: Underscore To Dash",
  "toix.regnize": "IX: Regnize",
  "toix.headerToBookmark": "IX: Header To Bookmark",
  "toix.mixer": "IX: Mixer",
  "toix.removeDuplicatedLines": "IX: Remove Duplicated Lines",
  "toix.removeEmptyLines": "IX: Remover linhas vazias",
  "toix.joinLines": "IX: Join Lines",
  "toix.splitLines": "IX: Split Lines",
  "toix.sortNumericallyAscending": "IX: Sort Numerically Ascending",
  "toix.sortNumericallyDescending": "IX: Sort Numerically Descending",
  "toix.indentOneSpace": "IX: Indent One Space",
  "toix.outdentOneSpace": "IX: Outdent One Space",
  "toix.breakLineAt": "IX: Dividir linhas longas",
  "toix.replaceRecipes": "IX: Replace Recipes",
  "toix.insertISODate": "IX: Insert ISO Date",
  "toix.insertISOTimeDate": "IX: Insert ISO TimeDate",
  "toix.insertUUID": "IX: Insert UUID",
  "toix.insertTextAtEnd": "IX: Insert Text At End",
  "toix.insertTextAtStart": "IX: Insert Text At Start",
  "toix.extractText": "IX: Extract Text"
}